{"Portland Trail Blazers": 0.622, "Phoenix Suns": 0.476, "Dallas Mavericks": 0.61, "Los Angeles Clippers": 0.683, "Orlando Magic": 0.305, "New York Knicks": 0.207, "Cleveland Cavaliers": 0.646, "Utah Jazz": 0.463, "Golden State Warriors": 0.817, "Detroit Pistons": 0.39, "Washington Wizards": 0.561, "Sacramento Kings": 0.354, "Indiana Pacers": 0.463, "Toronto Raptors": 0.598, "Philadelphia 76ers": 0.22, "Brooklyn Nets": 0.463, "Chicago Bulls": 0.61, "Boston Celtics": 0.488, "New Orleans Pelicans": 0.549, "Charlotte Hornets": 0.402, "Los Angeles Lakers": 0.256, "Houston Rockets": 0.683, "Denver Nuggets": 0.366, "Minnesota Timberwolves": 0.195, "Miami Heat": 0.451, "Milwaukee Bucks": 0.5, "Atlanta Hawks": 0.732, "Oklahoma City Thunder": 0.549, "Memphis Grizzlies": 0.671, "San Antonio Spurs": 0.671}